[
    {
        "id": 1,
        "text": "Home",
        "path": "list-item-1",
        "icon": "feather-home"
    },
    {
        "id": 2,
        "text": "Live Auction",
        "path": "list-item-2",
        "icon": "feather-heart"
    },
    {
        "id": 3,
        "text": "Explore Product",
        "path": "list-item-3",
        "icon": "feather-trending-up"
    },
    {
        "id": 4,
        "text": "Newest Item",
        "path": "list-item-4",
        "icon": "feather-trending-up"
    }
]
